{
 "name": "flare",
 "children": [
  {
   "name": "analytics",
   "children": [
    {
     "name": "Action",
     "children": [
      {"name":"Unturned","developer":"Nelson Sexton", "size": 100, "publisher":"Smartly Dressed Games","score_rank":83,"owners":18880955,"owners_variance":103860,"players_forever":13776952,"players_forever_variance":89645,"players_2weeks":967836,"players_2weeks_variance":24366,"average_forever":823,"average_2weeks":242,"median_forever":176,"median_2weeks":59,"ccu":26790},
      {"name":"Robocraft","developer":"Freejam", "size": 100, "publisher":"Freejam","score_rank":54,"owners":8612631,"owners_variance":71613,"players_forever":5699284,"players_forever_variance":58590,"players_2weeks":248047,"players_2weeks_variance":12352,"average_forever":1093,"average_2weeks":272,"median_forever":140,"median_2weeks":63,"ccu":6901},
      {"name":"Heroes & Generals", "size": 100, "developer":"Reto-Moto","publisher":"Reto-Moto","score_rank":29,"owners":8292331,"owners_variance":70314,"players_forever":5185610,"players_forever_variance":55943,"players_2weeks":232081,"players_2weeks_variance":11948,"average_forever":602,"average_2weeks":262,"median_forever":55,"median_2weeks":42,"ccu":7564}
     ]
    },
    {
     "name": "Adventure",
     "children": [
      {"appid":330580,"name":"Shark Attack Deathmatch 2","developer":"Lighthouse Games Studio","publisher":"Lighthouse Games Studio","score_rank":64,"owners":5967,"owners_variance":1916,"players_forever":5161,"players_forever_variance":1782,"players_2weeks":496,"players_2weeks_variance":685,"average_forever":55,"average_2weeks":100,"median_forever":25,"median_2weeks":100,"ccu":14},
      {"appid":339820,"name":"Starwalker","developer":"Rafael Barreto","publisher":"Rafael Barreto","score_rank":3,"owners":4516,"owners_variance":1667,"players_forever":491,"players_forever_variance":678,"players_2weeks":0,"players_2weeks_variance":0,"average_forever":81,"average_2weeks":0,"median_forever":81,"median_2weeks":0,"ccu":0},
      {"appid":327960,"name":"Journey of the King","developer":"DigitalWorldEntertainment","publisher":"DigitalWorldEntertainment","score_rank":13,"owners":4355,"owners_variance":1637,"players_forever":806,"players_forever_variance":704,"players_2weeks":0,"players_2weeks_variance":0,"average_forever":22,"average_2weeks":0,"median_forever":26,"median_2weeks":0,"ccu":0},
      {"appid":371520,"name":"Bounty Train","developer":"Corbie Games","publisher":"Daedalic Entertainment","score_rank":57,"owners":4838,"owners_variance":1725,"players_forever":3871,"players_forever_variance":1543,"players_2weeks":470,"players_2weeks_variance":920,"average_forever":779,"average_2weeks":7,"median_forever":485,"median_2weeks":7,"ccu":10},
      {"appid":321830,"name":"Cavern Kings","developer":"Vine","publisher":"Vine","score_rank":80,"owners":9838,"owners_variance":2461,"players_forever":8225,"players_forever_variance":2250,"players_2weeks":0,"players_2weeks_variance":0,"average_forever":453,"average_2weeks":0,"median_forever":296,"median_2weeks":0,"ccu":4},
      {"appid":332760,"name":"Friendship Club","developer":"Force Of Habit, Clockwork Cuckoo","publisher":"Force Of Habit","score_rank":70,"owners":3387,"owners_variance":1444,"players_forever":1735,"players_forever_variance":1282,"players_2weeks":524,"players_2weeks_variance":1026,"average_forever":34,"average_2weeks":6,"median_forever":44,"median_2weeks":6,"ccu":0},
      {"appid":398680,"name":"Ace of Words","developer":"ZeroBit Games","publisher":"Ocean Media LLC","score_rank":62,"owners":4838,"owners_variance":1725,"players_forever":3226,"players_forever_variance":1409,"players_2weeks":1227,"players_2weeks_variance":1073,"average_forever":238,"average_2weeks":261,"median_forever":243,"median_2weeks":278,"ccu":5},
      {"appid":325730,"name":"The Hive","developer":"Skydome Entertainment","publisher":"Skydome Entertainment","score_rank":39,"owners":5000,"owners_variance":1754,"players_forever":4032,"players_forever_variance":1575,"players_2weeks":462,"players_2weeks_variance":903,"average_forever":90,"average_2weeks":33,"median_forever":72,"median_2weeks":33,"ccu":2},
      {"appid":333380,"name":"SilverQuest: Gaiden","developer":"Wolfgame","publisher":"Wolfgame","score_rank":14,"owners":5000,"owners_variance":1754,"players_forever":524,"players_forever_variance":1026,"players_2weeks":0,"players_2weeks_variance":0,"average_forever":4,"average_2weeks":0,"median_forever":4,"median_2weeks":0,"ccu":0},
      {"appid":276870,"name":"Dwelvers","developer":"Rasmus Ljunggren","publisher":"Dancing Devils","score_rank":64,"owners":5645,"owners_variance":1864,"players_forever":5322,"players_forever_variance":1810,"players_2weeks":0,"players_2weeks_variance":0,"average_forever":311,"average_2weeks":0,"median_forever":170,"median_2weeks":0,"ccu":0},
      {"appid":408740,"name":"Pro Gamer Manager","developer":"Millenway Studios","publisher":"Millenway Studios","score_rank":31,"owners":6612,"owners_variance":2017,"players_forever":4838,"players_forever_variance":1725,"players_2weeks":1935,"players_2weeks_variance":1091,"average_forever":273,"average_2weeks":138,"median_forever":247,"median_2weeks":138,"ccu":33},
      {"appid":354910,"name":"Indie Assault","developer":"Imagination Vent, LLC","publisher":"Imagination Vent, LLC","score_rank":2,"owners":5967,"owners_variance":1916,"players_forever":0,"players_forever_variance":0,"players_2weeks":0,"players_2weeks_variance":0,"average_forever":0,"average_2weeks":0,"median_forever":0,"median_2weeks":0,"ccu":0},
      {"appid":311800,"name":"Black Ice","developer":"Super Duper Garrett Cooper","publisher":"Super Duper Garrett Cooper","score_rank":99,"owners":6612,"owners_variance":2017,"players_forever":5645,"players_forever_variance":1864,"players_2weeks":470,"players_2weeks_variance":920,"average_forever":422,"average_2weeks":143,"median_forever":283,"median_2weeks":143,"ccu":1},
      {"appid":340030,"name":"Dungeon of gain","developer":"Defroids team","publisher":"Defroids team","score_rank":0,"owners":5967,"owners_variance":1916,"players_forever":496,"players_forever_variance":685,"players_2weeks":0,"players_2weeks_variance":0,"average_forever":8,"average_2weeks":0,"median_forever":8,"median_2weeks":0,"ccu":0},
      {"appid":293480,"name":"FRONTIERS","developer":"AAD Productions","publisher":"AAD Productions","score_rank":52,"owners":5806,"owners_variance":1890,"players_forever":4838,"players_forever_variance":1725,"players_2weeks":744,"players_2weeks_variance":839,"average_forever":135,"average_2weeks":3,"median_forever":92,"median_2weeks":4,"ccu":0},
      {"appid":411120,"name":"Galaxy Admirals","developer":"Jetdogs Studios","publisher":"Jetdogs Studios","score_rank":92,"owners":3226,"owners_variance":1409,"players_forever":1735,"players_forever_variance":1282,"players_2weeks":1487,"players_2weeks_variance":1187,"average_forever":152,"average_2weeks":142,"median_forever":204,"median_2weeks":207,"ccu":56},
      {"appid":406090,"name":"Lost Moon","developer":"Eplixe","publisher":"Eplixe","score_rank":32,"owners":6129,"owners_variance":1942,"players_forever":466,"players_forever_variance":644,"players_2weeks":462,"players_2weeks_variance":903,"average_forever":13,"average_2weeks":20,"median_forever":13,"median_2weeks":20,"ccu":0},
      {"appid":259450,"name":"Drifter","developer":"Celsius Game Studios","publisher":"Celsius Game Studios","score_rank":52,"owners":8870,"owners_variance":2336,"players_forever":7903,"players_forever_variance":2205,"players_2weeks":0,"players_2weeks_variance":0,"average_forever":61,"average_2weeks":0,"median_forever":34,"median_2weeks":0,"ccu":0},
      {"appid":357330,"name":"Space Beast Terror Fright","developer":"nornware AB","publisher":"nornware AB","score_rank":92,"owners":3871,"owners_variance":1543,"players_forever":3709,"players_forever_variance":1511,"players_2weeks":1385,"players_2weeks_variance":1565,"average_forever":241,"average_2weeks":28,"median_forever":239,"median_2weeks":43,"ccu":7},
      {"appid":272230,"name":"Sub Rosa","developer":"Cryptic Sea","publisher":"Devolver Digital","score_rank":"","owners":4677,"owners_variance":1696,"players_forever":4677,"players_forever_variance":1696,"players_2weeks":1290,"players_2weeks_variance":891,"average_forever":497,"average_2weeks":104,"median_forever":432,"median_2weeks":198,"ccu":14},
      {"appid":402160,"name":"Star Command Galaxies","developer":"Warballoon","publisher":"Warballoon","score_rank":25,"owners":5000,"owners_variance":1754,"players_forever":2580,"players_forever_variance":1260,"players_2weeks":0,"players_2weeks_variance":0,"average_forever":75,"average_2weeks":0,"median_forever":65,"median_2weeks":0,"ccu":1},
      {"appid":284910,"name":"Purgatory: War of the Damned","developer":"Ironsun Studios","publisher":"KISS ltd","score_rank":25,"owners":6129,"owners_variance":1942,"players_forever":968,"players_forever_variance":771,"players_2weeks":0,"players_2weeks_variance":0,"average_forever":3,"average_2weeks":0,"median_forever":3,"median_2weeks":0,"ccu":0},
      {"appid":324470,"name":"SinaRun","developer":"Princesseuh","publisher":"Princesseuh","score_rank":80,"owners":4032,"owners_variance":1575,"players_forever":2580,"players_forever_variance":1260,"players_2weeks":645,"players_2weeks_variance":630,"average_forever":163,"average_2weeks":10,"median_forever":177,"median_2weeks":14,"ccu":8},
      {"appid":386710,"name":"StoryMode - A Game About Crafting","developer":"Nicholas Hydock","publisher":"Nicholas Hydock","score_rank":34,"owners":5000,"owners_variance":1754,"players_forever":941,"players_forever_variance":1302,"players_2weeks":0,"players_2weeks_variance":0,"average_forever":8,"average_2weeks":0,"median_forever":13,"median_2weeks":0,"ccu":1},
      {"appid":342870,"name":"Corona MotorSport","developer":"LucasGame","publisher":"LucasGame","score_rank":6,"owners":4193,"owners_variance":1606,"players_forever":1935,"players_forever_variance":1091,"players_2weeks":0,"players_2weeks_variance":0,"average_forever":14,"average_2weeks":0,"median_forever":7,"median_2weeks":0,"ccu":0},
      {"appid":363270,"name":"O3DX","developer":"Egamea Game Studios","publisher":"JRB Technologies","score_rank":39,"owners":5645,"owners_variance":1864,"players_forever":2903,"players_forever_variance":1336,"players_2weeks":470,"players_2weeks_variance":920,"average_forever":184,"average_2weeks":303,"median_forever":200,"median_2weeks":303,"ccu":2},
      {"appid":280440,"name":"M.A.V.","developer":"Bombdog Studios","publisher":"Bombdog Studios","score_rank":43,"owners":3871,"owners_variance":1543,"players_forever":3548,"players_forever_variance":1478,"players_2weeks":462,"players_2weeks_variance":903,"average_forever":95,"average_2weeks":15,"median_forever":39,"median_2weeks":15,"ccu":0},
      {"appid":382260,"name":"8Bit Fiesta","developer":"Frozen Dev","publisher":"Frozen Dev","score_rank":92,"owners":3226,"owners_variance":1409,"players_forever":2097,"players_forever_variance":1136,"players_2weeks":524,"players_2weeks_variance":1026,"average_forever":334,"average_2weeks":140,"median_forever":423,"median_2weeks":140,"ccu":4},
      {"appid":288220,"name":"Backstage Pass","developer":"sakevisual","publisher":"sakevisual","score_rank":64,"owners":3709,"owners_variance":1511,"players_forever":3548,"players_forever_variance":1478,"players_2weeks":0,"players_2weeks_variance":0,"average_forever":660,"average_2weeks":0,"median_forever":766,"median_2weeks":0,"ccu":0},
      {"appid":385130,"name":"DvDrum, Ultimate Drum Simulator!","developer":"DarkTigerDevelop","publisher":"DarkTigerDevelop","score_rank":31,"owners":3871,"owners_variance":1543,"players_forever":1048,"players_forever_variance":1451,"players_2weeks":1048,"players_2weeks_variance":1451,"average_forever":5565,"average_2weeks":1098,"median_forever":11081,"median_2weeks":2192,"ccu":1},
      {"appid":369560,"name":"The Story Goes On","developer":"Scarecrow Arts","publisher":"KISS ltd","score_rank":89,"owners":3064,"owners_variance":1373,"players_forever":1613,"players_forever_variance":996,"players_2weeks":0,"players_2weeks_variance":0,"average_forever":251,"average_2weeks":0,"median_forever":303,"median_2weeks":0,"ccu":2},
      {"appid":308520,"name":"Minimon","developer":"Minimon Team","publisher":"Minimon Team","score_rank":17,"owners":5483,"owners_variance":1837,"players_forever":3871,"players_forever_variance":1543,"players_2weeks":0,"players_2weeks_variance":0,"average_forever":177,"average_2weeks":0,"median_forever":200,"median_2weeks":0,"ccu":5},
      {"appid":370590,"name":"Gem Wars: Attack of the Jiblets","developer":"Queen Birdface Productions","publisher":"Queen Birdface Productions","score_rank":100,"owners":3226,"owners_variance":1409,"players_forever":1613,"players_forever_variance":996,"players_2weeks":466,"players_2weeks_variance":644,"average_forever":374,"average_2weeks":562,"median_forever":494,"median_2weeks":562,"ccu":0},
      {"appid":291250,"name":"Paragon","developer":"Meteoric Games","publisher":"Meteoric Games","score_rank":22,"owners":3709,"owners_variance":1511,"players_forever":3709,"players_forever_variance":1511,"players_2weeks":470,"players_2weeks_variance":920,"average_forever":128,"average_2weeks":33,"median_forever":121,"median_2weeks":33,"ccu":0},
      {"appid":246880,"name":"Recruits","developer":"QUByte Interactive, Commotion Games Pty Ltd","publisher":"Commotion Games Pty Ltd","score_rank":5,"owners":4838,"owners_variance":1725,"players_forever":2580,"players_forever_variance":1260,"players_2weeks":0,"players_2weeks_variance":0,"average_forever":65,"average_2weeks":0,"median_forever":78,"median_2weeks":0,"ccu":0},
      {"appid":410340,"name":"Liftoff","developer":"LuGus Studios","publisher":"LuGus Studios","score_rank":59,"owners":2258,"owners_variance":1179,"players_forever":2097,"players_forever_variance":1136,"players_2weeks":1452,"players_2weeks_variance":945,"average_forever":220,"average_2weeks":192,"median_forever":225,"median_2weeks":330,"ccu":35},
      {"appid":368340,"name":"CrossCode","developer":"Radical Fish Games","publisher":"Deck13","score_rank":100,"owners":2419,"owners_variance":1220,"players_forever":2258,"players_forever_variance":1179,"players_2weeks":466,"players_2weeks_variance":644,"average_forever":233,"average_2weeks":187,"median_forever":246,"median_2weeks":187,"ccu":9},
      {"appid":351990,"name":"Drive Any Track","developer":"FOAM Entertainment, Firebrand Games","publisher":"FOAM Entertainment","score_rank":89,"owners":3871,"owners_variance":1543,"players_forever":3871,"players_forever_variance":1543,"players_2weeks":645,"players_2weeks_variance":630,"average_forever":434,"average_2weeks":54,"median_forever":248,"median_2weeks":63,"ccu":4},
      {"appid":337820,"name":"The Mims Beginning","developer":"Squatting Penguins","publisher":"Squatting Penguins","score_rank":83,"owners":3709,"owners_variance":1511,"players_forever":3387,"players_forever_variance":1444,"players_2weeks":0,"players_2weeks_variance":0,"average_forever":160,"average_2weeks":0,"median_forever":115,"median_2weeks":0,"ccu":4},
      {"appid":348460,"name":"Bierzerkers","developer":"Shield Break Studios","publisher":"Shield Break Studios","score_rank":49,"owners":4032,"owners_variance":1575,"players_forever":3871,"players_forever_variance":1543,"players_2weeks":968,"players_2weeks_variance":771,"average_forever":76,"average_2weeks":31,"median_forever":54,"median_2weeks":53,"ccu":2},
      {"appid":402220,"name":"Lift It","developer":"89AM Studio","publisher":"89AM Studio","score_rank":52,"owners":3548,"owners_variance":1478,"players_forever":1774,"players_forever_variance":1045,"players_2weeks":466,"players_2weeks_variance":644,"average_forever":304,"average_2weeks":331,"median_forever":356,"median_2weeks":331,"ccu":0},
      {"appid":366290,"name":"Carp Fishing Simulator","developer":"Dangerous Derk Interactive","publisher":"Dangerous Derk Interactive","score_rank":28,"owners":3709,"owners_variance":1511,"players_forever":2419,"players_forever_variance":1220,"players_2weeks":0,"players_2weeks_variance":0,"average_forever":154,"average_2weeks":0,"median_forever":106,"median_2weeks":0,"ccu":6},
      {"appid":264440,"name":"Children of Liberty","developer":"Lantana Games","publisher":"Lantana Games","score_rank":3,"owners":3226,"owners_variance":1409,"players_forever":645,"players_forever_variance":630,"players_2weeks":0,"players_2weeks_variance":0,"average_forever":80,"average_2weeks":0,"median_forever":81,"median_2weeks":0,"ccu":0},
      {"appid":409590,"name":"Kingdoms","developer":"Max Peskov","publisher":"Max Peskov","score_rank":43,"owners":2580,"owners_variance":1260,"players_forever":2258,"players_forever_variance":1179,"players_2weeks":744,"players_2weeks_variance":839,"average_forever":98,"average_2weeks":19,"median_forever":103,"median_2weeks":22,"ccu":9},
      {"appid":363360,"name":"Interstellar Rift","developer":"Split Polygon","publisher":"Split Polygon","score_rank":59,"owners":5161,"owners_variance":1782,"players_forever":4516,"players_forever_variance":1667,"players_2weeks":462,"players_2weeks_variance":903,"average_forever":571,"average_2weeks":1,"median_forever":303,"median_2weeks":1,"ccu":11},
      {"appid":312430,"name":"Sovereignty: Crown of Kings","developer":"Gothic Labs, The Lordz Games Studio","publisher":"Slitherine Ltd.","score_rank":45,"owners":3871,"owners_variance":1543,"players_forever":3709,"players_forever_variance":1511,"players_2weeks":0,"players_2weeks_variance":0,"average_forever":1880,"average_2weeks":0,"median_forever":1680,"median_2weeks":0,"ccu":9},
      {"appid":407420,"name":"Gabe Newell Simulator","developer":"Antonio Renna","publisher":"Antonio Renna","score_rank":6,"owners":2903,"owners_variance":1336,"players_forever":1452,"players_forever_variance":945,"players_2weeks":491,"players_2weeks_variance":678,"average_forever":163,"average_2weeks":9,"median_forever":192,"median_2weeks":9,"ccu":4},
      {"appid":318090,"name":"Dicetiny","developer":"Fakedice","publisher":"Fakedice","score_rank":36,"owners":3226,"owners_variance":1409,"players_forever":3064,"players_forever_variance":1373,"players_2weeks":968,"players_2weeks_variance":771,"average_forever":71,"average_2weeks":23,"median_forever":50,"median_2weeks":43,"ccu":12},
      {"appid":268930,"name":"Malevolence: The Sword of Ahkranox","developer":"Visual Outbreak","publisher":"Visual Outbreak","score_rank":43,"owners":2454,"owners_variance":1518,"players_forever":2209,"players_forever_variance":1440,"players_2weeks":0,"players_2weeks_variance":0,"average_forever":1217,"average_2weeks":0,"median_forever":351,"median_2weeks":0,"ccu":0},
      {"appid":341710,"name":"Crest","developer":"Eat Create Sleep","publisher":"Eat Create Sleep","score_rank":41,"owners":2903,"owners_variance":1336,"players_forever":2580,"players_forever_variance":1260,"players_2weeks":524,"players_2weeks_variance":1026,"average_forever":137,"average_2weeks":1,"median_forever":79,"median_2weeks":1,"ccu":0},
      {"appid":330520,"name":"Tail Drift","developer":"Attract Mode Games","publisher":"Right Pedal Studios","score_rank":19,"owners":4516,"owners_variance":1667,"players_forever":0,"players_forever_variance":0,"players_2weeks":0,"players_2weeks_variance":0,"average_forever":0,"average_2weeks":0,"median_forever":0,"median_2weeks":0,"ccu":0},
      {"appid":350150,"name":"Scraps","developer":"Moment Studio","publisher":"Moment Studio","score_rank":54,"owners":2419,"owners_variance":1220,"players_forever":1290,"players_forever_variance":891,"players_2weeks":736,"players_2weeks_variance":831,"average_forever":106,"average_2weeks":44,"median_forever":59,"median_2weeks":70,"ccu":0},
      {"appid":358080,"name":"No Turning Back: The Pixel Art Action-Adventure Roguelike","developer":"ColloseusX, cpmilan","publisher":"ColloseusX","score_rank":"","owners":3064,"owners_variance":1373,"players_forever":462,"players_forever_variance":903,"players_2weeks":0,"players_2weeks_variance":0,"average_forever":159,"average_2weeks":0,"median_forever":159,"median_2weeks":0,"ccu":0},
      {"appid":404370,"name":"Tracks and Turrets","developer":"FingerPunch Games","publisher":"FingerPunch Games","score_rank":"","owners":2097,"owners_variance":1136,"players_forever":0,"players_forever_variance":0,"players_2weeks":0,"players_2weeks_variance":0,"average_forever":0,"average_2weeks":0,"median_forever":0,"median_2weeks":0,"ccu":0},
      {"appid":321390,"name":"Zone 22","developer":"Nordic Legacy","publisher":"Nordic Legacy","score_rank":11,"owners":1935,"owners_variance":1091,"players_forever":0,"players_forever_variance":0,"players_2weeks":0,"players_2weeks_variance":0,"average_forever":0,"average_2weeks":0,"median_forever":0,"median_2weeks":0,"ccu":0},
      {"appid":286240,"name":"Dog Sled Saga","developer":"Trichotomy","publisher":"Trichotomy","score_rank":92,"owners":4193,"owners_variance":1606,"players_forever":4032,"players_forever_variance":1575,"players_2weeks":0,"players_2weeks_variance":0,"average_forever":260,"average_2weeks":0,"median_forever":220,"median_2weeks":0,"ccu":0}
     ]
    },
    {
     "name": "MMO",
     "children": [

       {"appid":349450,"name":"Dark Forester","developer":"Morozov Sergey","publisher":"Morozov Sergey","score_rank":28,"owners":1613,"owners_variance":996,"players_forever":491,"players_forever_variance":678,"players_2weeks":462,"players_2weeks_variance":903,"average_forever":14,"average_2weeks":15,"median_forever":14,"median_2weeks":15,"ccu":0},
       {"appid":309900,"name":"Sky Arena","developer":"Hammer Labs","publisher":"Hammer Labs, Deck13","score_rank":86,"owners":806,"owners_variance":704,"players_forever":645,"players_forever_variance":630,"players_2weeks":462,"players_2weeks_variance":903,"average_forever":16,"average_2weeks":10,"median_forever":17,"median_2weeks":10,"ccu":0},
       {"appid":362310,"name":"Dungeon League","developer":"Achebit","publisher":"Surprise Attack","score_rank":76,"owners":806,"owners_variance":704,"players_forever":484,"players_forever_variance":545,"players_2weeks":0,"players_2weeks_variance":0,"average_forever":3,"average_2weeks":0,"median_forever":3,"median_2weeks":0,"ccu":0},
       {"appid":402330,"name":"Press X to Not Die","developer":"All Seeing Eye Games","publisher":"All Seeing Eye Games","score_rank":76,"owners":1452,"owners_variance":945,"players_forever":1290,"players_forever_variance":891,"players_2weeks":736,"players_2weeks_variance":831,"average_forever":114,"average_2weeks":109,"median_forever":151,"median_2weeks":120,"ccu":7},
       {"appid":416360,"name":"Max's Big Bust - A Captain Nekorai Tale","developer":"Lached Up Games","publisher":"Lached Up Games","score_rank":100,"owners":968,"owners_variance":771,"players_forever":699,"players_forever_variance":789,"players_2weeks":699,"players_2weeks_variance":789,"average_forever":150,"average_2weeks":20,"median_forever":156,"median_2weeks":30,"ccu":0},
       {"appid":418000,"name":"Demented","developer":"VisualTech48","publisher":"Intercido","score_rank":11,"owners":1290,"owners_variance":891,"players_forever":0,"players_forever_variance":0,"players_2weeks":0,"players_2weeks_variance":0,"average_forever":0,"average_2weeks":0,"median_forever":0,"median_2weeks":0,"ccu":0},
       {"appid":371010,"name":"Nomad Fleet","developer":"Autarca","publisher":"Autarca","score_rank":95,"owners":968,"owners_variance":771,"players_forever":736,"players_forever_variance":831,"players_2weeks":1048,"players_2weeks_variance":1451,"average_forever":230,"average_2weeks":7,"median_forever":447,"median_2weeks":12,"ccu":1},
       {"appid":263920,"name":"Zombie Grinder","developer":"TwinDrills","publisher":"TwinDrills","score_rank":86,"owners":2903,"owners_variance":1336,"players_forever":2742,"players_forever_variance":1299,"players_2weeks":1290,"players_2weeks_variance":891,"average_forever":1277,"average_2weeks":265,"median_forever":1354,"median_2weeks":309,"ccu":18},
       {"appid":342540,"name":"Terminal Hacker - Into the Deep","developer":"SecuritySession.com","publisher":"SecuritySession.com","score_rank":7,"owners":991,"owners_variance":969,"players_forever":470,"players_forever_variance":920,"players_2weeks":0,"players_2weeks_variance":0,"average_forever":3,"average_2weeks":0,"median_forever":3,"median_2weeks":0,"ccu":1},
       {"appid":346460,"name":"Vector 36","developer":"Red River Studio LLC","publisher":"NA","score_rank":39,"owners":1227,"owners_variance":1073,"players_forever":982,"players_forever_variance":960,"players_2weeks":524,"players_2weeks_variance":1026,"average_forever":12178,"average_2weeks":2552,"median_forever":12337,"median_2weeks":2552,"ccu":1},
       {"appid":359840,"name":"Shift Happens","developer":"Klonk Games","publisher":"Klonk Games, Deck13","score_rank":100,"owners":1129,"owners_variance":833,"players_forever":806,"players_forever_variance":704,"players_2weeks":496,"players_2weeks_variance":685,"average_forever":127,"average_2weeks":73,"median_forever":154,"median_2weeks":73,"ccu":7},
       {"appid":386600,"name":"Pixel Fodder","developer":"Wacha","publisher":"wacha.ru","score_rank":62,"owners":1613,"owners_variance":996,"players_forever":462,"players_forever_variance":903,"players_2weeks":0,"players_2weeks_variance":0,"average_forever":78,"average_2weeks":0,"median_forever":78,"median_2weeks":0,"ccu":0},
       {"appid":418910,"name":"Idle Civilization","developer":"Very Simple Idea Studios","publisher":"Very Simple Idea Studios","score_rank":62,"owners":1613,"owners_variance":996,"players_forever":1129,"players_forever_variance":833,"players_2weeks":1129,"players_2weeks_variance":833,"average_forever":1365,"average_2weeks":1365,"median_forever":1209,"median_2weeks":1209,"ccu":0},
       {"appid":321270,"name":"UNLOVED","developer":"BlueEagle Productions","publisher":"Paul Schneider","score_rank":52,"owners":806,"owners_variance":704,"players_forever":484,"players_forever_variance":545,"players_2weeks":491,"players_2weeks_variance":678,"average_forever":345,"average_2weeks":144,"median_forever":345,"median_2weeks":144,"ccu":7},
       {"appid":384090,"name":"Sketch Tales","developer":"8D Studio","publisher":"8D Studio","score_rank":80,"owners":1935,"owners_variance":1091,"players_forever":1774,"players_forever_variance":1045,"players_2weeks":645,"players_2weeks_variance":630,"average_forever":171,"average_2weeks":73,"median_forever":165,"median_2weeks":75,"ccu":4},
       {"appid":404620,"name":"The Political Machine 2016","developer":"Stardock Entertainment","publisher":"Stardock Entertainment","score_rank":45,"owners":1774,"owners_variance":1045,"players_forever":1290,"players_forever_variance":891,"players_2weeks":1290,"players_2weeks_variance":891,"average_forever":123,"average_2weeks":123,"median_forever":79,"median_2weeks":79,"ccu":0},
       {"appid":396650,"name":"ACE Academy","developer":"PixelFade Studio","publisher":"PixelFade Studio","score_rank":95,"owners":1227,"owners_variance":1073,"players_forever":736,"players_forever_variance":831,"players_2weeks":736,"players_2weeks_variance":831,"average_forever":1283,"average_2weeks":40,"median_forever":2457,"median_2weeks":47,"ccu":0},
       {"appid":355420,"name":"Flamberge","developer":"Hydezeke","publisher":"Hydezeke","score_rank":76,"owners":982,"owners_variance":960,"players_forever":736,"players_forever_variance":831,"players_2weeks":0,"players_2weeks_variance":0,"average_forever":75,"average_2weeks":0,"median_forever":77,"median_2weeks":0,"ccu":0},
       {"appid":384540,"name":"J\u00e4s\u00f8n - Season I","developer":"Creative Monkeys Productions","publisher":"Creative Monkeys Productions","score_rank":"","owners":524,"owners_variance":1026,"players_forever":524,"players_forever_variance":1026,"players_2weeks":524,"players_2weeks_variance":1026,"average_forever":12,"average_2weeks":1,"median_forever":12,"median_2weeks":1,"ccu":0},
       {"appid":386930,"name":"Dragonflight","developer":"Dragonflight LLC","publisher":"Blackthorn Media LLC","score_rank":76,"owners":736,"owners_variance":831,"players_forever":491,"players_forever_variance":678,"players_2weeks":462,"players_2weeks_variance":903,"average_forever":16163,"average_2weeks":234,"median_forever":16163,"median_2weeks":234,"ccu":1},
       {"appid":325300,"name":"BEARZERKERS","developer":"Wildgrass","publisher":"Wildgrass","score_rank":100,"owners":491,"owners_variance":678,"players_forever":0,"players_forever_variance":0,"players_2weeks":0,"players_2weeks_variance":0,"average_forever":0,"average_2weeks":0,"median_forever":0,"median_2weeks":0,"ccu":0},
       {"appid":340210,"name":"Predestination","developer":"Brain and Nerd Ltd","publisher":"Brain and Nerd Ltd","score_rank":41,"owners":2097,"owners_variance":1136,"players_forever":1774,"players_forever_variance":1045,"players_2weeks":496,"players_2weeks_variance":685,"average_forever":1656,"average_2weeks":260,"median_forever":241,"median_2weeks":260,"ccu":0},
       {"appid":372590,"name":"Grand Designer","developer":"Ignishot","publisher":"Ignishot","score_rank":100,"owners":524,"owners_variance":1026,"players_forever":524,"players_forever_variance":1026,"players_2weeks":0,"players_2weeks_variance":0,"average_forever":14,"average_2weeks":0,"median_forever":14,"median_2weeks":0,"ccu":0},
       {"appid":336790,"name":"KWAAN","developer":"Ankama Studio","publisher":"Ankama Games","score_rank":52,"owners":1613,"owners_variance":996,"players_forever":1631,"players_forever_variance":1205,"players_2weeks":466,"players_2weeks_variance":644,"average_forever":357,"average_2weeks":27,"median_forever":88,"median_2weeks":27,"ccu":2},
       {"appid":382050,"name":"Eon Altar","developer":"Flying Helmet Games","publisher":"Flying Helmet Games","score_rank":70,"owners":491,"owners_variance":678,"players_forever":491,"players_forever_variance":678,"players_2weeks":0,"players_2weeks_variance":0,"average_forever":215,"average_2weeks":0,"median_forever":215,"median_2weeks":0,"ccu":0},
       {"appid":405240,"name":"Queen Under The Mountain","developer":"Michael Todd Games","publisher":"Michael Todd Games","score_rank":52,"owners":645,"owners_variance":630,"players_forever":923,"players_forever_variance":1278,"players_2weeks":0,"players_2weeks_variance":0,"average_forever":7,"average_2weeks":0,"median_forever":7,"median_2weeks":0,"ccu":0},
       {"appid":397860,"name":"Carnivore Land","developer":"dwCrew","publisher":"dwCrew","score_rank":57,"owners":491,"owners_variance":678,"players_forever":491,"players_forever_variance":678,"players_2weeks":0,"players_2weeks_variance":0,"average_forever":357,"average_2weeks":0,"median_forever":357,"median_2weeks":0,"ccu":1},
       {"appid":372970,"name":"Cash_Out","developer":"Untouch","publisher":"Untouch","score_rank":100,"owners":744,"owners_variance":839,"players_forever":744,"players_forever_variance":839,"players_2weeks":496,"players_2weeks_variance":685,"average_forever":43,"average_2weeks":2,"median_forever":81,"median_2weeks":2,"ccu":0},
       {"appid":389230,"name":"Fish or Die","developer":"Thirsten Studios","publisher":"Thirsten Studios","score_rank":100,"owners":524,"owners_variance":1026,"players_forever":0,"players_forever_variance":0,"players_2weeks":0,"players_2weeks_variance":0,"average_forever":0,"average_2weeks":0,"median_forever":0,"median_2weeks":0,"ccu":0},
       {"appid":361040,"name":"Doom & Destiny Advanced","developer":"Heartbit Interactive","publisher":"Heartbit Interactive","score_rank":97,"owners":806,"owners_variance":704,"players_forever":466,"players_forever_variance":644,"players_2weeks":0,"players_2weeks_variance":0,"average_forever":442,"average_2weeks":0,"median_forever":442,"median_2weeks":0,"ccu":7},
       {"appid":378280,"name":"Pump-Action Captain","developer":"Type Advantage, Brain Dead Software","publisher":"Teknik Gaming","score_rank":16,"owners":645,"owners_variance":630,"players_forever":0,"players_forever_variance":0,"players_2weeks":0,"players_2weeks_variance":0,"average_forever":0,"average_2weeks":0,"median_forever":0,"median_2weeks":0,"ccu":0},
       {"appid":338040,"name":"Bears Can't Drift!?","developer":"Arran Langmead","publisher":"Strangely Named Studio","score_rank":86,"owners":484,"owners_variance":545,"players_forever":491,"players_forever_variance":678,"players_2weeks":0,"players_2weeks_variance":0,"average_forever":34,"average_2weeks":0,"median_forever":34,"median_2weeks":0,"ccu":1},
       {"appid":383010,"name":"JamG","developer":"Ern\u0151 Kir\u00e1ly","publisher":"Ern\u0151 Kir\u00e1ly","score_rank":83,"owners":524,"owners_variance":1026,"players_forever":0,"players_forever_variance":0,"players_2weeks":0,"players_2weeks_variance":0,"average_forever":0,"average_2weeks":0,"median_forever":0,"median_2weeks":0,"ccu":0},
       {"appid":399580,"name":"Nuclear Shot","developer":"Maruf ARTUKO\u011eLU, Muhammed DA\u011eLI","publisher":"Maruf ARTUKO\u011eLU","score_rank":25,"owners":736,"owners_variance":831,"players_forever":491,"players_forever_variance":678,"players_2weeks":462,"players_2weeks_variance":903,"average_forever":47,"average_2weeks":2,"median_forever":47,"median_2weeks":2,"ccu":0},
       {"appid":406400,"name":"Axes and Arrows","developer":"The Net Champs","publisher":"The Net Champs","score_rank":16,"owners":524,"owners_variance":1026,"players_forever":524,"players_forever_variance":1026,"players_2weeks":0,"players_2weeks_variance":0,"average_forever":2,"average_2weeks":0,"median_forever":2,"median_2weeks":0,"ccu":0},
       {"appid":290020,"name":"LogicBots","developer":"Incandescent Games","publisher":"Incandescent Games","score_rank":89,"owners":968,"owners_variance":771,"players_forever":968,"players_forever_variance":771,"players_2weeks":0,"players_2weeks_variance":0,"average_forever":168,"average_2weeks":0,"median_forever":247,"median_2weeks":0,"ccu":0},
       {"ppid":308060,"name":"Black The Fall","developer":"Sand Sailor Studio","publisher":"Sand Sailor Studio","score_rank":54,"owners":1290,"owners_variance":891,"players_forever":1129,"players_forever_variance":833,"players_2weeks":0,"players_2weeks_variance":0,"average_forever":64,"average_2weeks":0,"median_forever":69,"median_2weeks":0,"ccu":0}

     ]
    }
   ]
  }
 ]
}